aws_lambda_env_modeler/__init__.py
aws_lambda_env_modeler/modeler.py
aws_lambda_env_modeler/modeler_impl.py
aws_lambda_env_modeler/py.typed
aws_lambda_env_modeler/types.py
aws_lambda_env_modeler-2.0.1.dist-info/METADATA
aws_lambda_env_modeler-2.0.1.dist-info/WHEEL
aws_lambda_env_modeler-2.0.1.dist-info/licenses/LICENSE
aws_lambda_env_modeler-2.0.1.dist-info/RECORD
