Metadata-Version: 2.4
Name: aws_lambda_env_modeler
Version: 2.0.1
Summary: AWS-Lambda-Env-Modeler is a Python library designed to simplify the process of managing and validating environment variables in your AWS Lambda functions.
Project-URL: Repository, https://github.com/ran-isenberg/aws-lambda-env-modeler
Project-URL: Issue tracker, https://github.com/ran-isenberg/aws-lambda-env-modeler/issues
Project-URL: Releases, https://github.com/ran-isenberg/aws-lambda-env-modeler/releases
Author: Ran Isenberg
License-Expression: MIT-0
License-File: LICENSE
Keywords: aws lambda,aws serverless,environment variables parser,lambda environment variables,serverless best practices
Classifier: Development Status :: 5 - Production/Stable
Classifier: Intended Audience :: Developers
Classifier: License :: OSI Approved :: MIT License
Classifier: Natural Language :: English
Classifier: Programming Language :: Python :: 3.9
Classifier: Programming Language :: Python :: 3.10
Classifier: Programming Language :: Python :: 3.11
Classifier: Programming Language :: Python :: 3.12
Classifier: Programming Language :: Python :: 3.13
Requires-Python: <4,>=3.9.0
Requires-Dist: pydantic<3,>=2.0.0
